{
  "unique": { "names": 49157, "lastNames": 475, "firstNames": 3007 },
  "top": {
    "lastNames": [
      { "name": "Barton", "count": 143 },
      { "name": "Lang", "count": 136 },
      { "name": "Ortiz", "count": 135 },
      { "name": "Hilll", "count": 134 },
      { "name": "Hills", "count": 130 },
      { "name": "Batz", "count": 129 },
      { "name": "Terry", "count": 129 },
      { "name": "123Becker", "count": 128 },
      { "name": "Johns", "count": 128 },
      { "name": "Romaguera", "count": 128 }
    ],
    "firstNames": [
      { "name": "Tara", "count": 34 },
      { "name": "Andreanne", "count": 32 },
      { "name": "Ulices", "count": 31 },
      { "name": "Stephania", "count": 31 },
      { "name": "Summer", "count": 31 },
      { "name": "Keon", "count": 31 },
      { "name": "Milo", "count": 30 },
      { "name": "Manley", "count": 30 },
      { "name": "Kayley", "count": 30 },
      { "name": "Heath", "count": 30 }
    ]
  },
  "list": {
    "specifically": [
      "Graham, Mckenna",
      "Marvin, Garfield",
      "McLaughlin, Mariah",
      "Lang, Agustina",
      "Bradtke, Nikko",
      "Adams, Luis",
      "Lehner, Matilde",
      "Ortiz, Anita",
      "Koch, Berry",
      "Cartwright, Nicolas",
      "Fisher, Elmo",
      "Kunze, Gertrude",
      "Stanton, Davin",
      "O'Conner, Constantin",
      "Runolfsdottir, Roy",
      "Rogahn, Colby",
      "Tromp, Ryley",
      "Hoppe, Stanley",
      "Shanahan, Bethel",
      "Hills, Samanta",
      "Lynch, Norma",
      "Bahringer, Lennie",
      "Tillman, Madison"
    ],
    "modified": [
      "Graham, Garfield",
      "Marvin, Mariah",
      "McLaughlin, Agustina",
      "Lang, Nikko",
      "Bradtke, Luis",
      "Adams, Matilde",
      "Lehner, Anita",
      "Ortiz, Berry",
      "Koch, Nicolas",
      "Cartwright, Elmo",
      "Fisher, Gertrude",
      "Kunze, Davin",
      "Stanton, Constantin",
      "O'Conner, Roy",
      "Runolfsdottir, Colby",
      "Rogahn, Ryley",
      "Tromp, Stanley",
      "Hoppe, Bethel",
      "Shanahan, Samanta",
      "Hills, Norma",
      "Lynch, Lennie",
      "Bahringer, Madison",
      "Tillman, Mckenna"
    ]
  }
}
